git_sync/__init__.py
git_sync/__main__.py
git_sync/core.py
git_sync-0.2.0.dist-info/METADATA
git_sync-0.2.0.dist-info/WHEEL
git_sync-0.2.0.dist-info/entry_points.txt
git_sync-0.2.0.dist-info/top_level.txt
git_sync-0.2.0.dist-info/RECORD
