Metadata-Version: 2.1
Name: git-sync
Version: 0.2.0
Summary: The git_sync module
Home-page: UNKNOWN
Author: Jon Crall
Author-email: erotemic@gmail.com
License: Apache 2
Platform: UNKNOWN
Classifier: Development Status :: 3 - Alpha
Classifier: Intended Audience :: Developers
Classifier: Topic :: Software Development :: Libraries :: Python Modules
Classifier: Topic :: Utilities
Classifier: License :: OSI Approved :: Apache Software License
Classifier: Programming Language :: Python :: 3.6
Classifier: Programming Language :: Python :: 3.7
Classifier: Programming Language :: Python :: 3.8
Classifier: Programming Language :: Python :: 3.9
Classifier: Programming Language :: Python :: 3.10
Classifier: Programming Language :: Python :: 3.11
Requires-Python: >=3.6
Requires-Dist: ubelt
Provides-Extra: all
Requires-Dist: coverage ; extra == 'all'
Requires-Dist: pytest ; extra == 'all'
Requires-Dist: pytest-cov ; extra == 'all'
Requires-Dist: ubelt ; extra == 'all'
Requires-Dist: xdoctest ; extra == 'all'
Provides-Extra: all-strict
Requires-Dist: coverage (==4.3.4) ; extra == 'all-strict'
Requires-Dist: pytest-cov ; extra == 'all-strict'
Requires-Dist: pytest (==3.3.1) ; extra == 'all-strict'
Requires-Dist: ubelt (==0.8.0) ; extra == 'all-strict'
Requires-Dist: xdoctest (==0.3.0) ; extra == 'all-strict'
Provides-Extra: optional
Provides-Extra: optional-strict
Provides-Extra: runtime-strict
Requires-Dist: ubelt (==0.8.0) ; extra == 'runtime-strict'
Provides-Extra: tests
Requires-Dist: coverage ; extra == 'tests'
Requires-Dist: pytest ; extra == 'tests'
Requires-Dist: pytest-cov ; extra == 'tests'
Requires-Dist: xdoctest ; extra == 'tests'
Provides-Extra: tests-strict
Requires-Dist: coverage (==4.3.4) ; extra == 'tests-strict'
Requires-Dist: pytest-cov ; extra == 'tests-strict'
Requires-Dist: pytest (==3.3.1) ; extra == 'tests-strict'
Requires-Dist: xdoctest (==0.3.0) ; extra == 'tests-strict'
